neurom/HiDeNN_PDE.py
neurom/__init__.py
neurom/generate_evaluation_points_2D.py
neurom/main.py
neurom/main_NonIntegralMixedForm.py
neurom/Post/Evaluation_wrt_NumSolution.py
neurom/Post/Plots.py
neurom/Post/__init__.py
neurom/src/MyHeaders.py
neurom/src/PDE_Library.py
neurom/src/Pre_processing.py
neurom/src/Training.py
neurom/src/__init__.py
neurom/src/gard_test.py
neurom_py-4.0.6.dist-info/licenses/LICENSE
neurom_py-4.0.6.dist-info/METADATA
neurom_py-4.0.6.dist-info/WHEEL
neurom_py-4.0.6.dist-info/entry_points.txt
neurom_py-4.0.6.dist-info/top_level.txt
neurom_py-4.0.6.dist-info/RECORD
