Metadata-Version: 2.4
Name: NeuROM-Py
Version: 4.0.6
Summary: NeuROM, a NN-PGD architecture based on the HiDeNN Framework (Finite Element Neural Network Interpolation)
Home-page: https://github.com/AlexandreDabySeesaram/NeuROM
Author: Alexandre Daby-Seesaram, Katerina Skardova, Martin Genet
Author-email: [alexandre.daby-seesaram,katerina.skardova,martin.genet]@polytechnique.edu
License: GPLv3
Classifier: Programming Language :: Python :: 3
Classifier: License :: OSI Approved :: GNU General Public License v3 (GPLv3)
Classifier: Operating System :: OS Independent
License-File: LICENSE
Requires-Dist: argparse
Requires-Dist: torch
Requires-Dist: matplotlib
Requires-Dist: meshio
Requires-Dist: numpy
Requires-Dist: ipython
Requires-Dist: scipy
Requires-Dist: gmsh
Requires-Dist: vtk
Requires-Dist: pyvista
Dynamic: author
Dynamic: author-email
Dynamic: classifier
Dynamic: description
Dynamic: description-content-type
Dynamic: home-page
Dynamic: license
Dynamic: license-file
Dynamic: requires-dist
Dynamic: summary
